smilei_slider.py
smilei_slider-0.1.0.dist-info/LICENSE
smilei_slider-0.1.0.dist-info/METADATA
smilei_slider-0.1.0.dist-info/WHEEL
smilei_slider-0.1.0.dist-info/top_level.txt
smilei_slider-0.1.0.dist-info/RECORD
